import_a-0.0.25.dist-info/licenses/LICENSE
important/__init__.py
important/location.py
important/redis.py
important/snowflake.py
important/azure_tts/__init__.py
important/azure_tts/config.py
important/azure_tts/fetch.py
important/azure_tts/token.py
important/conf/redis.yaml
important/conf/snowflake.yaml
important/graph/__init__.py
important/graph/dag.py
important/honest_llm/__init__.py
important/honest_llm/chat.py
important/k8s/__init__.py
important/k8s/helm.py
important/k8s/kube/__init__.py
important/k8s/kube/crud.py
important/k8s/kube/crud_async.py
important/k8s/kube/utils.py
important/llmsdk/__init__.py
important/llmsdk/anthropic.py
important/llmsdk/chat.py
important/llmsdk/groq.py
important/llmsdk/openai.py
important/logger/bucket.py
important/openai/__init__.py
important/openai/config.py
important/redis_cache/__init__.py
important/redis_cache/redis_client.py
important/redis_cache/redis_util.py
important/redis_cache/test/run_redis.py
important/shell/__init__.py
important/shell/aws.py
important/shell/base.py
important/shell/color.py
important/shell/pandas/__init__.py
important/shell/pandas/async_pandas.py
important/smasher/__init__.py
important/smasher/smasher.py
important/stateful/__init__.py
important/stateful/base.py
important/transcribe/__init__.py
important/transcribe/whisper.py
important/weaviate/__init__.py
important/weaviate/crud.py
important/weaviate/utils.py
important/xilabs/__init__.py
important/xilabs/axilabs.py
important/xilabs/utils.py
important/xilabs/xilabs.py
import_a-0.0.25.dist-info/METADATA
import_a-0.0.25.dist-info/WHEEL
import_a-0.0.25.dist-info/top_level.txt
import_a-0.0.25.dist-info/RECORD
