Metadata-Version: 2.4
Name: import-a
Version: 0.0.25
Summary: A folder of functions and classes that are easy to import
Author-email: "Xiaochen Zhang (Ray)" <ray@fireworkhq.com>, "Shi Feng (Shawn)" <shawn@fireworkhq.com>, Nikhil Bapat <nikhil.bapat@fireworkhq.com>, Sanjana Pradhan <sanjana.pradhan@fireworkhq.com>
License:                     GNU AFFERO GENERAL PUBLIC LICENSE
Project-URL: homepage, https://github.com/loopsocial/important
Project-URL: repository, https://github.com/loopsocial/important
Keywords: data science,data engineer
Classifier: Development Status :: 2 - Pre-Alpha
Classifier: Intended Audience :: End Users/Desktop
Classifier: License :: OSI Approved :: GNU General Public License v3 (GPLv3)
Classifier: Programming Language :: Python :: 3.6
Classifier: Programming Language :: Python :: 3.7
Classifier: Programming Language :: Python :: 3.8
Classifier: Programming Language :: Python :: 3.9
Classifier: Programming Language :: Python :: 3.10
Classifier: Programming Language :: Python :: 3.11
License-File: LICENSE
Requires-Dist: gallop
Requires-Dist: python-dotenv
Requires-Dist: pyyaml
Provides-Extra: all
Requires-Dist: redis; extra == "all"
Requires-Dist: snowflake-connector-python; extra == "all"
Requires-Dist: openai; extra == "all"
Requires-Dist: pydub==0.25.1; extra == "all"
Requires-Dist: weaviate-client==3.21.0; extra == "all"
Provides-Extra: kube
Requires-Dist: forgebox; extra == "kube"
Provides-Extra: redis
Requires-Dist: redis; extra == "redis"
Provides-Extra: redis-cache
Requires-Dist: redis; extra == "redis-cache"
Provides-Extra: snowflake
Requires-Dist: snowflake-connector-python; extra == "snowflake"
Provides-Extra: weaviate
Requires-Dist: weaviate-client==3.21.0; extra == "weaviate"
Provides-Extra: whisper
Requires-Dist: openai; extra == "whisper"
Requires-Dist: pydub==0.25.1; extra == "whisper"
Dynamic: license-file
